{
  "definitions": [
    {
      "title": "Carousel",
      "id": "carousel",
      "plugins": {
        "xwalk": {
          "page": {
            "resourceType": "core/franklin/components/block/v1/block",
            "template": {
              "name": "Carousel",
              "filter": "carousel"
            }
          }
        }
      }
    },
    {
      "title": "Slide",
      "id": "slide",
      "plugins": {
        "xwalk": {
          "page": {
            "resourceType": "core/franklin/components/block/v1/block/item",
            "template": {
              "name": "Slide",
              "model": "slide"
            }
          }
        }
      }
    }
  ],
  "models": [
    {
      "id": "slide",
      "fields": [
        {
          "component": "text",
          "name": "title",
          "label": "Title",
          "valueType": "string"
        },
        {
          "component": "richtext",
          "name": "description",
          "label": "Description",
          "valueType": "string"
        },
        {
          "component": "text",
          "name": "status",
          "label": "Status",
          "valueType": "string",
          "description": "e.g., Active, RECRUITING"
        },
        {
          "component": "text",
          "name": "phase",
          "label": "Phase",
          "valueType": "string",
          "description": "e.g., 3 (open-label)"
        },
        {
          "component": "text",
          "name": "conditions",
          "label": "Medical Conditions",
          "valueType": "string"
        },
        {
          "component": "aem-content",
          "name": "link",
          "label": "Link URL",
          "valueType": "string"
        },
        {
          "component": "select",
          "name": "progressPhase",
          "label": "Progress Phase",
          "valueType": "number",
          "description": "Number of dots to display (1-4)",
          "options": [
            { "name": "1", "value": 1 },
            { "name": "2", "value": 2 },
            { "name": "3", "value": 3 },
            { "name": "4", "value": 4 }
          ]
        }
      ]
    }
  ],
  "filters": [
    {
      "id": "carousel",
      "components": [
        "slide"
      ]
    }
  ]
}